delaunay_refine/delaunay_refine.py
delaunay_refine/refine.py
delaunay_refine/triangulation.py
delaunay_refine/utils.py
delaunay_refine-0.1.0.dist-info/LICENSE.txt
delaunay_refine-0.1.0.dist-info/METADATA
delaunay_refine-0.1.0.dist-info/WHEEL
delaunay_refine-0.1.0.dist-info/RECORD
