Metadata-Version: 2.3
Name: delaunay_refine
Version: 0.1.0
Summary: "Performs refinement on constrained Delaunay triangulation to geopandas geodataframes"
Author: stippe
Requires-Python: >=3.12
Classifier: Programming Language :: Python :: 3
Classifier: Programming Language :: Python :: 3.12
Classifier: Programming Language :: Python :: 3.13
Requires-Dist: geopandas (>=1.1.1,<2.0.0)
Requires-Dist: matplotlib (>=3.10.5,<4.0.0)
